hpc_connect/__init__.py
hpc_connect/__main__.py
hpc_connect/config.py
hpc_connect/discover.py
hpc_connect/hookspec.py
hpc_connect/launch.py
hpc_connect/pluginmanager.py
hpc_connect/py.typed
hpc_connect/schemas.py
hpc_connect/submit.py
hpc_connect/version.py
hpc_connect/command/__init__.py
hpc_connect/command/config.py
hpc_connect/command/launch.py
hpc_connect/command/submit.py
hpc_connect/templates/hpcc-submit.sh.in
hpc_connect/util/__init__.py
hpc_connect/util/collections.py
hpc_connect/util/dynamic_version.py
hpc_connect/util/string.py
hpc_connect/util/tengine.py
hpc_connect/util/time.py
hpc_connect-25.10.7.dist-info/licenses/LICENSE
hpcc_flux/__init__.py
hpcc_flux/discover.py
hpcc_flux/submit_api.py
hpcc_flux/submit_hl.py
hpcc_flux/templates/submit.sh.in
hpcc_mpi/__init__.py
hpcc_mpi/launch.py
hpcc_mpi/py.typed
hpcc_pbs/__init__.py
hpcc_pbs/discover.py
hpcc_pbs/py.typed
hpcc_pbs/submit.py
hpcc_pbs/templates/submit.sh.in
hpcc_slurm/__init__.py
hpcc_slurm/discover.py
hpcc_slurm/launch.py
hpcc_slurm/py.typed
hpcc_slurm/submit.py
hpcc_slurm/templates/submit.sh.in
hpcc_subprocess/__init__.py
hpcc_subprocess/py.typed
hpcc_subprocess/submit.py
hpcc_subprocess/templates/submit.sh.in
hpc_connect-25.10.7.dist-info/METADATA
hpc_connect-25.10.7.dist-info/WHEEL
hpc_connect-25.10.7.dist-info/entry_points.txt
hpc_connect-25.10.7.dist-info/top_level.txt
hpc_connect-25.10.7.dist-info/RECORD
