Metadata-Version: 2.4
Name: hpc-connect
Version: 25.10.7
Summary: hpc_connect: lightweight HPC submission and launching interfaces
Requires-Python: >=3.10
License-File: LICENSE
Requires-Dist: pluggy
Requires-Dist: jinja2
Requires-Dist: psutil
Requires-Dist: PyYAML
Requires-Dist: schema
Provides-Extra: dev
Requires-Dist: ruff; extra == "dev"
Requires-Dist: mypy; extra == "dev"
Requires-Dist: pytest; extra == "dev"
Dynamic: license-file
